CNCeleb/__init__.py
CNCeleb/_version.py
CNCeleb/data/cnceleb2_duration.txt.gz
pyannote.db.cnceleb-0.0.4.dist-info/LICENSE
pyannote.db.cnceleb-0.0.4.dist-info/METADATA
pyannote.db.cnceleb-0.0.4.dist-info/WHEEL
pyannote.db.cnceleb-0.0.4.dist-info/entry_points.txt
pyannote.db.cnceleb-0.0.4.dist-info/top_level.txt
pyannote.db.cnceleb-0.0.4.dist-info/RECORD
